Metadata-Version: 1.1
Name: npdl
Version: 0.4.0.1
Summary: Deep Learning Library based on pure Numpy
Home-page: http://numpydl.readthedocs.io
Author: Chao-Ming Wang
Author-email: oujago@gmail.com
License: MIT
Download-URL: https://github.com/oujago/NumpyDL
Keywords: deep learning library
Platform: UNKNOWN
Classifier: Intended Audience :: Developers
Classifier: Intended Audience :: Science/Research
Classifier: License :: OSI Approved :: MIT License
Classifier: Programming Language :: Python :: 3.6
Classifier: Programming Language :: Python :: 3.5
Classifier: Topic :: Scientific/Engineering :: Artificial Intelligence
